SegmentSignalPy.cp312-win_amd64.pyd
CPP Static Library/SegmentSignal.cpp
CPP Static Library/SegmentSignalFunctions.cpp
CPP Static Library/SegmentationResults.cpp
Python Extension/SegmentationResultsPy.cpp
Python Extension/module.cpp
SegmentSignalPy-0.1.2.dist-info/License.txt
SegmentSignalPy-0.1.2.dist-info/METADATA
SegmentSignalPy-0.1.2.dist-info/WHEEL
SegmentSignalPy-0.1.2.dist-info/top_level.txt
SegmentSignalPy-0.1.2.dist-info/RECORD
