Metadata-Version: 2.1
Name: SegmentSignalPy
Version: 0.1.2
Summary: Signal segmentation algorithm by S. Radhakrishnan, et al. This is a Python interface for the C++ algorithm.
License: Copyright (c) 2021-2024 Lance A. Endres
Project-URL: homepage, https://github.com/lendres/Segment-Signals
Requires-Python: >=3.11.0
